Metadata-Version: 2.1
Name: streamlit-tree-select-dark
Version: 0.0.17
Summary: A simple and elegant checkbox tree for Streamlit.
Home-page: https://github.com/manav148/streamlit_tree_select_dark
Author: Manav
Author-email: 
Classifier: Programming Language :: Python :: 3
Classifier: License :: OSI Approved :: MIT License
Classifier: Operating System :: OS Independent
Requires-Python: >=3.6
License-File: LICENSE
Requires-Dist: streamlit >=0.63
